coop_cms/__init__.py
coop_cms/admin.py
coop_cms/bs_forms.py
coop_cms/context_processors.py
coop_cms/coop_bar_cfg.py
coop_cms/exceptions.py
coop_cms/feeds.py
coop_cms/generic_views.py
coop_cms/logger.py
coop_cms/middleware.py
coop_cms/models.py
coop_cms/moves.py
coop_cms/optionals.py
coop_cms/perms_backends.py
coop_cms/secrets.py
coop_cms/settings.py
coop_cms/shortcuts.py
coop_cms/sitemap.py
coop_cms/test_runners.py
coop_cms/thumbnail_backend.py
coop_cms/translation.py
coop_cms/urls.py
coop_cms/widgets.py
coop_cms/apps/__init__.py
coop_cms/apps/basic_cms/__init__.py
coop_cms/apps/basic_cms/apps.py
coop_cms/apps/basic_cms/models.py
coop_cms/apps/basic_cms/tests.py
coop_cms/apps/basic_cms/translation.py
coop_cms/apps/basic_cms/migrations/0001_initial.py
coop_cms/apps/basic_cms/migrations/0002_auto_20150924_1433.py
coop_cms/apps/basic_cms/migrations/0003_auto_20160129_1524.py
coop_cms/apps/basic_cms/migrations/0004_auto_20161031_1401.py
coop_cms/apps/basic_cms/migrations/0005_auto_20190719_1408.py
coop_cms/apps/basic_cms/migrations/0006_alter_article_category_alter_article_id_and_more.py
coop_cms/apps/basic_cms/migrations/__init__.py
coop_cms/apps/basic_cms/templates/admin/basic_cms/navtree/change_form.html
coop_cms/apps/coop_bootstrap/__init__.py
coop_cms/apps/coop_bootstrap/apps.py
coop_cms/apps/coop_bootstrap/forms.py
coop_cms/apps/coop_bootstrap/static/bs/css/bootstrap-theme.css
coop_cms/apps/coop_bootstrap/static/bs/css/bootstrap-theme.min.css
coop_cms/apps/coop_bootstrap/static/bs/css/bootstrap.css
coop_cms/apps/coop_bootstrap/static/bs/css/bootstrap.min.css
coop_cms/apps/coop_bootstrap/static/bs/fonts/glyphicons-halflings-regular.eot
coop_cms/apps/coop_bootstrap/static/bs/fonts/glyphicons-halflings-regular.svg
coop_cms/apps/coop_bootstrap/static/bs/fonts/glyphicons-halflings-regular.ttf
coop_cms/apps/coop_bootstrap/static/bs/fonts/glyphicons-halflings-regular.woff
coop_cms/apps/coop_bootstrap/static/bs/js/bootstrap.js
apidev_coop_cms-1.6.12.dist-info/METADATA
apidev_coop_cms-1.6.12.dist-info/WHEEL
apidev_coop_cms-1.6.12.dist-info/top_level.txt
apidev_coop_cms-1.6.12.dist-info/RECORD
