Metadata-Version: 2.1
Name: apidev-coop-cms
Version: 1.6.12
Summary: Small CMS built around a tree navigation open to any django models
Home-page: https://github.com/ljean/coop_cms/
Download-URL: https://github.com/ljean/coop_cms/tarball/master
Author: Luc Jean
Author-email: ljean@apidev.fr
License: BSD
Classifier: Development Status :: 5 - Production/Stable
Classifier: Environment :: Web Environment
Classifier: Intended Audience :: Developers
Classifier: License :: OSI Approved :: BSD License
Classifier: Operating System :: OS Independent
Classifier: Programming Language :: Python
Classifier: Framework :: Django
Classifier: Natural Language :: English
Classifier: Natural Language :: French
Classifier: Topic :: Internet :: WWW/HTTP :: Dynamic Content
Classifier: Topic :: Internet :: WWW/HTTP :: WSGI :: Application
Requires-Dist: django<5.0,>=4.2
Requires-Dist: django-extensions
Requires-Dist: sorl-thumbnail
Requires-Dist: apidev-coop-colorbox>=1.6.0
Requires-Dist: apidev-coop-bar>=1.6.0
Requires-Dist: coop-html-editor>=1.4.0
Requires-Dist: feedparser
Requires-Dist: beautifulsoup4
Requires-Dist: model-mommy
Requires-Dist: unicode-slugify
